README.rst
qu.py
setup.py
qu.egg-info/PKG-INFO
qu.egg-info/SOURCES.txt
qu.egg-info/dependency_links.txt
qu.egg-info/entry_points.txt
qu.egg-info/not-zip-safe
qu.egg-info/requires.txt
qu.egg-info/top_level.txt